emdb/__init__.py
emdb/client.py
emdb/exceptions.py
emdb/utils.py
emdb/models/__init__.py
emdb/models/annotations.py
emdb/models/entry.py
emdb/models/files.py
emdb/models/lazy_entry.py
emdb/models/plots.py
emdb/models/search.py
emdb/models/validation.py
emdb-0.1.10.dist-info/licenses/LICENSE
emdb-0.1.10.dist-info/METADATA
emdb-0.1.10.dist-info/WHEEL
emdb-0.1.10.dist-info/top_level.txt
emdb-0.1.10.dist-info/RECORD
