Metadata-Version: 2.4
Name: emdb
Version: 0.1.10
Summary: A Python client for accessing the Electron Microscopy Data Bank (EMDB)
Author-email: Neli Fonseca <neli@ebi.ac.uk>
License: Apache 2
Project-URL: Homepage, https://www.ebi.ac.uk/emdb/
Project-URL: Documentation, https://emdb.readthedocs.io/en/latest/
Project-URL: Repository, https://github.com/emdb-empiar/emdb-api-wrapper
Project-URL: Bug Tracker, https://github.com/emdb-empiar/emdb-api-wrapper/issues
Keywords: EMDB,Electron Microscopy,Bioinformatics,Client
Classifier: Programming Language :: Python :: 3
Classifier: License :: OSI Approved :: Apache Software License
Classifier: Operating System :: OS Independent
Requires-Python: >=3.8
License-File: LICENSE
Requires-Dist: requests<3.0,>=2.0
Requires-Dist: matplotlib<4.0,>=3.5
Requires-Dist: pandas<3.0,>=2.3
Requires-Dist: pydantic<3.0,>=2.0
Provides-Extra: test
Requires-Dist: pytest>=8.0; extra == "test"
Requires-Dist: pytest-mock>=3.0; extra == "test"
Requires-Dist: pytest-cov>=4.0; extra == "test"
Requires-Dist: responses>=0.20; extra == "test"
Dynamic: license-file
